{
    "swagger": "2.0",
    "info": {
        "description": "CRUD Swagger",
        "title": "CRUD",
        "contact": {},
        "version": "1.0"
    },
    "basePath": "/",
    "paths": {
        "/users": {
            "get": {
                "description": "List all users",
                "consumes": [
                    "application/json"
                ],
                "produces": [
                    "application/json"
                ],
                "tags": [
                    "users"
                ],
                "responses": {
                    "200": {
                        "description": "string",
                        "schema": {
                            "type": "string"
                        }
                    }
                }
            },
            "post": {
                "description": "Create new user",
                "consumes": [
                    "application/json"
                ],
                "produces": [
                    "application/json"
                ],
                "tags": [
                    "createuser"
                ],
                "parameters": [
                    {
                        "description": "User Data",
                        "name": "user",
                        "in": "body",
                        "required": true,
                        "schema": {
                            "$ref": "#/definitions/models.User"
                        }
                    }
                ],
                "responses": {
                    "201": {
                        "description": "Created",
                        "schema": {
                            "$ref": "#/definitions/models.ResponseUser"
                        }
                    }
                }
            }
        }
    },
    "definitions": {
        "models.ResponseUser": {
            "type": "object",
            "required": [
                "email",
                "name"
            ],
            "properties": {
                "email": {
                    "type": "string"
                },
                "name": {
                    "type": "string"
                }
            }
        },
        "models.User": {
            "type": "object",
            "required": [
                "email",
                "name"
            ],
            "properties": {
                "email": {
                    "type": "string"
                },
                "name": {
                    "type": "string"
                },
                "password": {
                    "type": "string"
                }
            }
        }
    }
}